{
  "problem_id": "putnam_1962_a3",
  "dataset": "putnam",
  "timestamp": "2025-06-19T02:28:29.398100",
  "original_verification_pass": false,
  "hole_verification_pass": true,
  "holes": [
    {
      "hole_id": "hole_1",
      "original_proof": "exfalso\nsimp_all [Collinear, EuclideanSpace.segment_eq_image]\ntry norm_num\ntry linarith\ntry ring_nf at *\ntry field_simp at *\ntry nlinarith\ntry {aesop\n}"
    },
    {
      "hole_id": "hole_2",
      "original_proof": "exact hABC h\u2081\u2084"
    },
    {
      "hole_id": "hole_3",
      "original_proof": "exfalso\nexact h\u2081"
    },
    {
      "hole_id": "hole_4",
      "original_proof": "exact h\u2082"
    }
  ]
}