{
  "problem_id": "mathd_algebra_441",
  "dataset": "minif2f",
  "verification_count": 1,
  "max_verifications": 3,
  "original_verification_pass": true,
  "hole_verification_pass": true,
  "filled_verification_pass": true,
  "synthesized_verification_pass": true,
  "complete_solve_success": false,
  "original_tactics_test": {
    "hole_1": {
      "success": true,
      "error_message": null,
      "original_tactic": "ring"
    },
    "hole_2": {
      "success": true,
      "error_message": null,
      "original_tactic": "field_simp [h\u2080, pow_ne_zero, mul_comm, mul_assoc, mul_left_comm]"
    },
    "hole_3": {
      "success": true,
      "error_message": null,
      "original_tactic": "field_simp [h\u2080, pow_ne_zero, mul_comm, mul_assoc, mul_left_comm]"
    },
    "hole_4": {
      "success": true,
      "error_message": null,
      "original_tactic": "rw [h\u2081\u2083]"
    },
    "hole_5": {
      "success": true,
      "error_message": null,
      "original_tactic": "ring_nf"
    },
    "hole_6": {
      "success": true,
      "error_message": null,
      "original_tactic": "rw [h\u2082\u2081]"
    },
    "hole_7": {
      "success": true,
      "error_message": null,
      "original_tactic": "rw [h\u2081]\nrw [h\u2082]"
    },
    "hole_8": {
      "success": true,
      "error_message": null,
      "original_tactic": "exact pow_ne_zero 4 h\u2080"
    },
    "hole_9": {
      "success": true,
      "error_message": null,
      "original_tactic": "field_simp [h\u2084\u2081]\nring_nf"
    },
    "hole_10": {
      "success": true,
      "error_message": null,
      "original_tactic": "rw [h\u2084\u2083]\nnorm_num"
    },
    "hole_11": {
      "success": true,
      "error_message": null,
      "original_tactic": "rw [h\u2084\u2082]"
    },
    "hole_12": {
      "success": true,
      "error_message": null,
      "original_tactic": "rw [h\u2083]\nrw [h\u2084]"
    },
    "hole_13": {
      "success": true,
      "error_message": null,
      "original_tactic": "rw [h\u2085]"
    }
  },
  "successful_tactics": {
    "hole_1": "linarith",
    "hole_2": "ring",
    "hole_3": "ring",
    "hole_4": "linarith",
    "hole_5": "linarith",
    "hole_6": "linarith",
    "hole_7": "ring",
    "hole_8": "simpa",
    "hole_10": "linarith",
    "hole_11": "linarith",
    "hole_12": "linarith",
    "hole_13": "linarith"
  },
  "tactic_mapping": {
    "hole_1": "linarith",
    "hole_2": "ring",
    "hole_3": "ring",
    "hole_4": "linarith",
    "hole_5": "linarith",
    "hole_6": "linarith",
    "hole_7": "ring",
    "hole_8": "simpa",
    "hole_10": "linarith",
    "hole_11": "linarith",
    "hole_12": "linarith",
    "hole_13": "linarith",
    "hole_9": "admit"
  },
  "proof_state_tests": 50,
  "tactic_attempts": {
    "hole_1": [
      {
        "tactic": "norm_num",
        "success": false,
        "error_message": "Tactic status: Incomplete: open goals remain, goals remain: 1"
      },
      {
        "tactic": "linarith",
        "success": true,
        "error_message": null
      }
    ],
    "hole_2": [
      {
        "tactic": "norm_num",
        "success": false,
        "error_message": "Tactic status: Incomplete: open goals remain, goals remain: 1"
      },
      {
        "tactic": "linarith",
        "success": false,
        "error_message": "Lean error:\nlinarith failed to find a contradiction\ncase h1.h\nx : \u211d\nh\u2080 : x \u2260 0\nh\u2081\u2081 : 12 / (x * x) * (x ^ 4 / (14 * x)) * (35 / (3 * x)) = 12 / (x * x) * (x ^ 4 / (14 * x) * (35 / (3 * x)))\na\u271d : x ^ 4 / (14 * x) * (35 / (3 * x)) < x ^ 4 * 35 / (14 * x * (3 * x))\n\u22a2 False failed"
      },
      {
        "tactic": "nlinarith",
        "success": false,
        "error_message": "Lean error:\nlinarith failed to find a contradiction\ncase h1.h\nx : \u211d\nh\u2080 : x \u2260 0\nh\u2081\u2081 : 12 / (x * x) * (x ^ 4 / (14 * x)) * (35 / (3 * x)) = 12 / (x * x) * (x ^ 4 / (14 * x) * (35 / (3 * x)))\na\u271d : x ^ 4 / (14 * x) * (35 / (3 * x)) < x ^ 4 * 35 / (14 * x * (3 * x))\n\u22a2 False failed"
      },
      {
        "tactic": "omega",
        "success": false,
        "error_message": "Lean error:\nomega could not prove the goal:\nNo usable constraints found. You may need to unfold definitions so `omega` can see linear arithmetic facts about `Nat` and `Int`, which may also involve multiplication, division, and modular remainder by constants."
      },
      {
        "tactic": "ring",
        "success": true,
        "error_message": null
      }
    ],
    "hole_3": [
      {
        "tactic": "norm_num",
        "success": false,
        "error_message": "Tactic status: Incomplete: open goals remain, goals remain: 1"
      },
      {
        "tactic": "linarith",
        "success": false,
        "error_message": "Lean error:\nlinarith failed to find a contradiction\ncase h1.h\nx : \u211d\nh\u2080 : x \u2260 0\nh\u2081\u2081 : 12 / (x * x) * (x ^ 4 / (14 * x)) * (35 / (3 * x)) = 12 / (x * x) * (x ^ 4 / (14 * x) * (35 / (3 * x)))\nh\u2081\u2082 : x ^ 4 / (14 * x) * (35 / (3 * x)) = x ^ 4 * 35 / (14 * x * (3 * x))\na\u271d : 12 / (x * x) * (x ^ 4 * 35 / (14 * x * (3 * x))) < 12 * x ^ 4 * 35 / (x * x * (14 * x) * (3 * x))\n\u22a2 False failed"
      },
      {
        "tactic": "nlinarith",
        "success": false,
        "error_message": "Lean error:\nlinarith failed to find a contradiction\ncase h1.h\nx : \u211d\nh\u2080 : x \u2260 0\nh\u2081\u2081 : 12 / (x * x) * (x ^ 4 / (14 * x)) * (35 / (3 * x)) = 12 / (x * x) * (x ^ 4 / (14 * x) * (35 / (3 * x)))\nh\u2081\u2082 : x ^ 4 / (14 * x) * (35 / (3 * x)) = x ^ 4 * 35 / (14 * x * (3 * x))\na\u271d : 12 / (x * x) * (x ^ 4 * 35 / (14 * x * (3 * x))) < 12 * x ^ 4 * 35 / (x * x * (14 * x) * (3 * x))\n\u22a2 False failed"
      },
      {
        "tactic": "omega",
        "success": false,
        "error_message": "Lean error:\nomega could not prove the goal:\nNo usable constraints found. You may need to unfold definitions so `omega` can see linear arithmetic facts about `Nat` and `Int`, which may also involve multiplication, division, and modular remainder by constants."
      },
      {
        "tactic": "ring",
        "success": true,
        "error_message": null
      }
    ],
    "hole_4": [
      {
        "tactic": "norm_num",
        "success": false,
        "error_message": "Tactic status: Incomplete: open goals remain, goals remain: 1"
      },
      {
        "tactic": "linarith",
        "success": true,
        "error_message": null
      }
    ],
    "hole_5": [
      {
        "tactic": "norm_num",
        "success": false,
        "error_message": "Tactic status: Incomplete: open goals remain, goals remain: 1"
      },
      {
        "tactic": "linarith",
        "success": true,
        "error_message": null
      }
    ],
    "hole_6": [
      {
        "tactic": "norm_num",
        "success": false,
        "error_message": "Tactic status: Incomplete: open goals remain, goals remain: 1"
      },
      {
        "tactic": "linarith",
        "success": true,
        "error_message": null
      }
    ],
    "hole_7": [
      {
        "tactic": "norm_num",
        "success": false,
        "error_message": "Tactic status: Incomplete: open goals remain, goals remain: 1"
      },
      {
        "tactic": "linarith",
        "success": false,
        "error_message": "Lean error:\nlinarith failed to find a contradiction\ncase h1.h\nx : \u211d\nh\u2080 : x \u2260 0\nh\u2081 : 12 / (x * x) * (x ^ 4 / (14 * x)) * (35 / (3 * x)) = 12 * x ^ 4 * 35 / (x * x * (14 * x) * (3 * x))\nh\u2082 : x * x * (14 * x) * (3 * x) = 42 * x ^ 4\na\u271d : 12 / (x * x) * (x ^ 4 / (14 * x)) * (35 / (3 * x)) < 12 * x ^ 4 * 35 / (42 * x ^ 4)\n\u22a2 False failed"
      },
      {
        "tactic": "nlinarith",
        "success": false,
        "error_message": "Lean error:\nlinarith failed to find a contradiction\ncase h1.h\nx : \u211d\nh\u2080 : x \u2260 0\nh\u2081 : 12 / (x * x) * (x ^ 4 / (14 * x)) * (35 / (3 * x)) = 12 * x ^ 4 * 35 / (x * x * (14 * x) * (3 * x))\nh\u2082 : x * x * (14 * x) * (3 * x) = 42 * x ^ 4\na\u271d : 12 / (x * x) * (x ^ 4 / (14 * x)) * (35 / (3 * x)) < 12 * x ^ 4 * 35 / (42 * x ^ 4)\n\u22a2 False failed"
      },
      {
        "tactic": "omega",
        "success": false,
        "error_message": "Lean error:\nomega could not prove the goal:\nNo usable constraints found. You may need to unfold definitions so `omega` can see linear arithmetic facts about `Nat` and `Int`, which may also involve multiplication, division, and modular remainder by constants."
      },
      {
        "tactic": "ring",
        "success": true,
        "error_message": null
      }
    ],
    "hole_8": [
      {
        "tactic": "norm_num",
        "success": false,
        "error_message": "Tactic status: Incomplete: open goals remain, goals remain: 1"
      },
      {
        "tactic": "linarith",
        "success": false,
        "error_message": "Lean error:\nlinarith failed to find a contradiction\ncase h\nx : \u211d\nh\u2080 : x \u2260 0\nh\u2081 : 12 / (x * x) * (x ^ 4 / (14 * x)) * (35 / (3 * x)) = 12 * x ^ 4 * 35 / (x * x * (14 * x) * (3 * x))\nh\u2082 : x * x * (14 * x) * (3 * x) = 42 * x ^ 4\nh\u2083 : 12 / (x * x) * (x ^ 4 / (14 * x)) * (35 / (3 * x)) = 12 * x ^ 4 * 35 / (42 * x ^ 4)\na\u271d : x ^ 4 = 0\n\u22a2 False failed"
      },
      {
        "tactic": "nlinarith",
        "success": false,
        "error_message": "Lean error:\nlinarith failed to find a contradiction\ncase h\nx : \u211d\nh\u2080 : x \u2260 0\nh\u2081 : 12 / (x * x) * (x ^ 4 / (14 * x)) * (35 / (3 * x)) = 12 * x ^ 4 * 35 / (x * x * (14 * x) * (3 * x))\nh\u2082 : x * x * (14 * x) * (3 * x) = 42 * x ^ 4\nh\u2083 : 12 / (x * x) * (x ^ 4 / (14 * x)) * (35 / (3 * x)) = 12 * x ^ 4 * 35 / (42 * x ^ 4)\na\u271d : x ^ 4 = 0\n\u22a2 False failed"
      },
      {
        "tactic": "omega",
        "success": false,
        "error_message": "Lean error:\nomega could not prove the goal:\nNo usable constraints found. You may need to unfold definitions so `omega` can see linear arithmetic facts about `Nat` and `Int`, which may also involve multiplication, division, and modular remainder by constants."
      },
      {
        "tactic": "ring",
        "success": false,
        "error_message": "Tactic status: Incomplete: open goals remain, goals remain: 1"
      },
      {
        "tactic": "ring_nf",
        "success": false,
        "error_message": "Tactic status: Incomplete: open goals remain, goals remain: 1"
      },
      {
        "tactic": "simp",
        "success": false,
        "error_message": "Tactic status: Incomplete: open goals remain, goals remain: 1"
      },
      {
        "tactic": "simpa",
        "success": true,
        "error_message": null
      }
    ],
    "hole_9": [
      {
        "tactic": "norm_num",
        "success": false,
        "error_message": "Tactic status: Incomplete: open goals remain, goals remain: 1"
      },
      {
        "tactic": "linarith",
        "success": false,
        "error_message": "Lean error:\nlinarith failed to find a contradiction\ncase h1.h\nx : \u211d\nh\u2080 : x \u2260 0\nh\u2081 : 12 / (x * x) * (x ^ 4 / (14 * x)) * (35 / (3 * x)) = 12 * x ^ 4 * 35 / (x * x * (14 * x) * (3 * x))\nh\u2082 : x * x * (14 * x) * (3 * x) = 42 * x ^ 4\nh\u2083 : 12 / (x * x) * (x ^ 4 / (14 * x)) * (35 / (3 * x)) = 12 * x ^ 4 * 35 / (42 * x ^ 4)\nh\u2084\u2081 : x ^ 4 \u2260 0\na\u271d : 12 * x ^ 4 * 35 / (42 * x ^ 4) < 12 * 35 / 42\n\u22a2 False failed"
      },
      {
        "tactic": "nlinarith",
        "success": false,
        "error_message": "Lean error:\nlinarith failed to find a contradiction\ncase h1.h\nx : \u211d\nh\u2080 : x \u2260 0\nh\u2081 : 12 / (x * x) * (x ^ 4 / (14 * x)) * (35 / (3 * x)) = 12 * x ^ 4 * 35 / (x * x * (14 * x) * (3 * x))\nh\u2082 : x * x * (14 * x) * (3 * x) = 42 * x ^ 4\nh\u2083 : 12 / (x * x) * (x ^ 4 / (14 * x)) * (35 / (3 * x)) = 12 * x ^ 4 * 35 / (42 * x ^ 4)\nh\u2084\u2081 : x ^ 4 \u2260 0\na\u271d : 12 * x ^ 4 * 35 / (42 * x ^ 4) < 12 * 35 / 42\n\u22a2 False failed"
      },
      {
        "tactic": "omega",
        "success": false,
        "error_message": "Lean error:\nomega could not prove the goal:\nNo usable constraints found. You may need to unfold definitions so `omega` can see linear arithmetic facts about `Nat` and `Int`, which may also involve multiplication, division, and modular remainder by constants."
      },
      {
        "tactic": "ring",
        "success": false,
        "error_message": "Tactic status: Incomplete: open goals remain, goals remain: 1"
      },
      {
        "tactic": "ring_nf",
        "success": false,
        "error_message": "Tactic status: Incomplete: open goals remain, goals remain: 1"
      },
      {
        "tactic": "simp",
        "success": false,
        "error_message": "Lean error:\nsimp made no progress"
      },
      {
        "tactic": "simpa",
        "success": false,
        "error_message": "Lean error:\ntactic 'assumption' failed\nx : \u211d\nh\u2080 : x \u2260 0\nh\u2081 : 12 / (x * x) * (x ^ 4 / (14 * x)) * (35 / (3 * x)) = 12 * x ^ 4 * 35 / (x * x * (14 * x) * (3 * x))\nh\u2082 : x * x * (14 * x) * (3 * x) = 42 * x ^ 4\nh\u2083 : 12 / (x * x) * (x ^ 4 / (14 * x)) * (35 / (3 * x)) = 12 * x ^ 4 * 35 / (42 * x ^ 4)\nh\u2084\u2081 : x ^ 4 \u2260 0\n\u22a2 12 * x ^ 4 * 35 / (42 * x ^ 4) = 12 * 35 / 42"
      },
      {
        "tactic": "field_simp",
        "success": false,
        "error_message": "Tactic status: Incomplete: open goals remain, goals remain: 1"
      },
      {
        "tactic": "positivity",
        "success": false,
        "error_message": "Lean error:\nnot a positivity goal"
      },
      {
        "tactic": "norm_cast",
        "success": false,
        "error_message": "Tactic status: Incomplete: open goals remain, goals remain: 1"
      }
    ],
    "hole_10": [
      {
        "tactic": "norm_num",
        "success": false,
        "error_message": "Tactic status: Incomplete: open goals remain, goals remain: 1"
      },
      {
        "tactic": "linarith",
        "success": true,
        "error_message": null
      }
    ],
    "hole_11": [
      {
        "tactic": "norm_num",
        "success": false,
        "error_message": "Tactic status: Incomplete: open goals remain, goals remain: 1"
      },
      {
        "tactic": "linarith",
        "success": true,
        "error_message": null
      }
    ],
    "hole_12": [
      {
        "tactic": "norm_num",
        "success": false,
        "error_message": "Tactic status: Incomplete: open goals remain, goals remain: 1"
      },
      {
        "tactic": "linarith",
        "success": true,
        "error_message": null
      }
    ],
    "hole_13": [
      {
        "tactic": "norm_num",
        "success": false,
        "error_message": "Tactic status: Incomplete: open goals remain, goals remain: 1"
      },
      {
        "tactic": "linarith",
        "success": true,
        "error_message": null
      }
    ]
  },
  "processing_time_seconds": 27.756433,
  "constraint_satisfied": true,
  "tactics_replaced": 12,
  "timestamp": "2025-06-19T01:08:59.461255"
}