{
  "problem_id": "putnam_1978_a6",
  "dataset": "putnam",
  "timestamp": "2025-06-14T11:24:57.041170",
  "header_file": "header.lean",
  "problem_file": "problem.lean",
  "original_verification_pass": false,
  "filled_verification_pass": false,
  "hole_verification_pass": false,
  "holes": [
    {
      "hole_id": "hole_1",
      "original_proof": "intro pair hp\nsimp only [Set.mem_setOf_eq] at hp \u22a2\nrcases hp with \u27e8P, hP, Q, hQ, hpair, hdist\u27e9\nexact \u27e8P, hP, Q, hQ, hpair\u27e9",
      "best_tactic": null,
      "method": "unigram_tactics",
      "original_verification_pass": true,
      "hole_verification_pass": true,
      "filled_verification_pass": true,
      "tactics_tried": [],
      "successful_tactics": [],
      "failed_tactics": []
    },
    {
      "hole_id": "hole_2",
      "original_proof": "apply Set.ncard_le_ncard h\u2083",
      "best_tactic": null,
      "method": "unigram_tactics",
      "original_verification_pass": true,
      "hole_verification_pass": true,
      "filled_verification_pass": true,
      "tactics_tried": [],
      "successful_tactics": [],
      "failed_tactics": []
    },
    {
      "hole_id": "hole_3",
      "original_proof": "ext pair\nsimp [Set.mem_image, Set.mem_offDiag, Finset.mem_coe, Finset.mem_product]\naesop",
      "best_tactic": null,
      "method": "unigram_tactics",
      "original_verification_pass": true,
      "hole_verification_pass": true,
      "filled_verification_pass": true,
      "tactics_tried": [],
      "successful_tactics": [],
      "failed_tactics": []
    }
  ]
}