{
  "Real": "Mathlib.Data.Real.Basic",
  "Nat.all": "Init.Data.Nat.Fold",
  "Bool.or": "Init.Prelude",
  "Max.max": "Init.Prelude",
  "nlinarith": "Mathlib.Tactic.Linarith.Frontend",
  "when": "Mathlib.Control.Combinators",
  "Alternative": "Init.Control.Basic",
  "norm_num": "Mathlib.Tactic.NormNum.Core",
  "Nat": "Init.Prelude",
  "by_cases": "Mathlib.Logic.Basic",
  "Lean.maxHeartbeats": "Lean.CoreM",
  "Rat": "Batteries.Data.Rat.Basic",
  "Bool.and": "Init.Prelude",
  "linarith": "Mathlib.Tactic.Linarith.Frontend",
  "Nat.any": "Init.Data.Nat.Fold",
  "Nat.zero": "Init.Prelude",
  "pow_two_nonneg": "Mathlib.Algebra.Order.Ring.Unbundled.Basic"
}